ndx_microscopy/spec/ndx-microscopy.extensions.yaml
ndx_microscopy/spec/ndx-microscopy.namespace.yaml
ndx_microscopy/__init__.py
ndx_microscopy/ndx_microscopy.py
ndx_microscopy/testing/__init__.py
ndx_microscopy/testing/_mock.py
ndx_microscopy-0.3.0.dist-info/METADATA
ndx_microscopy-0.3.0.dist-info/WHEEL
ndx_microscopy-0.3.0.dist-info/licenses/LICENSE.txt
ndx_microscopy-0.3.0.dist-info/RECORD
