Metadata-Version: 2.4
Name: ndx-microscopy
Version: 0.3.0
Summary: An NWB extension to demonstrate the TAB proposal for enhancements to optical physiology neurodata types.
Project-URL: Homepage, https://github.com/CatalystNeuro/ndx-microscopy
Project-URL: Documentation, https://ndx-microscopy.readthedocs.io/
Project-URL: Bug Tracker, https://github.com/CatalystNeuro/ndx-microscopy/issues
Project-URL: Discussions, https://github.com/CatalystNeuro/ndx-microscopy/discussions
Project-URL: Changelog, https://github.com/CatalystNeuro/ndx-microscopy/blob/main/CHANGELOG.md
Author-email: Alessandra Trapani <alessandra.trapani@catalystneuro.com>, Cody Baker <cody.baker@catalystneuro.com>
License: BSD-3
License-File: LICENSE.txt
Keywords: NWB,NeurodataWithoutBorders,ndx-extension,nwb-extension
Classifier: Intended Audience :: Developers
Classifier: Intended Audience :: Science/Research
Classifier: License :: OSI Approved :: BSD License
Classifier: Programming Language :: Python :: 3.11
Requires-Dist: hdmf>=3.14.1
Requires-Dist: ndx-ophys-devices==0.2.0
Requires-Dist: pynwb>=2.8.0
